ekn/__init__.py
ekn/negr.py
ekn/data/1.txt
ekn/data/teor/Screenshot_1.png
ekn/data/teor/Screenshot_10.png
ekn/data/teor/Screenshot_100.png
ekn/data/teor/Screenshot_101.png
ekn/data/teor/Screenshot_102.png
ekn/data/teor/Screenshot_103.png
ekn/data/teor/Screenshot_104.png
ekn/data/teor/Screenshot_105.png
ekn/data/teor/Screenshot_106.png
ekn/data/teor/Screenshot_107.png
ekn/data/teor/Screenshot_108.png
ekn/data/teor/Screenshot_109.png
ekn/data/teor/Screenshot_11.png
ekn/data/teor/Screenshot_110.png
ekn/data/teor/Screenshot_111.png
ekn/data/teor/Screenshot_112.png
ekn/data/teor/Screenshot_113.png
ekn/data/teor/Screenshot_114.png
ekn/data/teor/Screenshot_115.png
ekn/data/teor/Screenshot_116.png
ekn/data/teor/Screenshot_117.png
ekn/data/teor/Screenshot_118.png
ekn/data/teor/Screenshot_119.png
ekn/data/teor/Screenshot_12.png
ekn/data/teor/Screenshot_120.png
ekn/data/teor/Screenshot_121.png
ekn/data/teor/Screenshot_13.png
ekn/data/teor/Screenshot_14.png
ekn/data/teor/Screenshot_15.png
ekn/data/teor/Screenshot_16.png
ekn/data/teor/Screenshot_17.png
ekn/data/teor/Screenshot_18.png
ekn/data/teor/Screenshot_19.png
ekn/data/teor/Screenshot_2.png
ekn/data/teor/Screenshot_20.png
ekn/data/teor/Screenshot_21.png
ekn/data/teor/Screenshot_22.png
ekn/data/teor/Screenshot_23.png
ekn/data/teor/Screenshot_24.png
ekn/data/teor/Screenshot_25.png
ekn/data/teor/Screenshot_26.png
ekn/data/teor/Screenshot_27.png
ekn/data/teor/Screenshot_28.png
ekn/data/teor/Screenshot_29.png
ekn/data/teor/Screenshot_3.png
ekn/data/teor/Screenshot_30.png
ekn/data/teor/Screenshot_31.png
ekn/data/teor/Screenshot_32.png
ekn/data/teor/Screenshot_33.png
ekn/data/teor/Screenshot_34.png
ekn/data/teor/Screenshot_35.png
ekn/data/teor/Screenshot_36.png
ekn/data/teor/Screenshot_37.png
ekn/data/teor/Screenshot_38.png
ekn/data/teor/Screenshot_39.png
ekn/data/teor/Screenshot_4.png
ekn/data/teor/Screenshot_40.png
ekn/data/teor/Screenshot_41.png
ekn/data/teor/Screenshot_42.png
ekn/data/teor/Screenshot_43.png
ekn-0.2.1.dist-info/METADATA
ekn-0.2.1.dist-info/WHEEL
ekn-0.2.1.dist-info/top_level.txt
ekn-0.2.1.dist-info/RECORD
