Metadata-Version: 2.1
Name: ekn
Version: 0.2.1
Keywords: ekn
Classifier: Programming Language :: Python :: 3.11
Classifier: License :: OSI Approved :: MIT License
Classifier: Operating System :: OS Independent
Requires-Python: >=3.6
Requires-Dist: requests >=2.25.1
Requires-Dist: Pillow
